data_printer/__init__.py
data_printer-0.0.8.dist-info/LICENSE
data_printer-0.0.8.dist-info/METADATA
data_printer-0.0.8.dist-info/WHEEL
data_printer-0.0.8.dist-info/top_level.txt
data_printer-0.0.8.dist-info/RECORD
