Metadata-Version: 2.1
Name: data-printer
Version: 0.0.8
Summary: **data_printer** - data printer and dumper
Home-page: https://github.com/darviarush/python-data-printer
Author: Kosmina O. Yaroslav
Author-email: darviarush@mail.ru
License: MIT
Platform: any
Classifier: Development Status :: 4 - Beta
Classifier: Topic :: Text Processing
Classifier: License :: OSI Approved :: MIT License
Classifier: Operating System :: OS Independent
Classifier: Programming Language :: Python :: 3
Classifier: Programming Language :: Python :: 3.3
Classifier: Programming Language :: Python :: 3.4
Classifier: Programming Language :: Python :: 3.5
Classifier: Programming Language :: Python :: 3.6
Classifier: Programming Language :: Python :: 3.7
Requires-Python: >=3.6
License-File: LICENSE
